ai_builder_photo.py
ai_builder_photo-1.0.0.dist-info/METADATA
ai_builder_photo-1.0.0.dist-info/WHEEL
ai_builder_photo-1.0.0.dist-info/top_level.txt
ai_builder_photo-1.0.0.dist-info/RECORD
