Metadata-Version: 2.4
Name: ai-builder-photo
Version: 1.0.0
Summary: AI Builder Photo - генератор изображений диалогов в стиле мессенджера
Home-page: https://github.com/yourusername/ai-builder-photo
Author: hokemka
Author-email: your.email@example.com
Project-URL: Bug Reports, https://github.com/yourusername/ai-builder-photo/issues
Project-URL: Source, https://github.com/yourusername/ai-builder-photo
Keywords: ai,builder,photo,chat,screenshot,generator,messenger,image
Classifier: Development Status :: 5 - Production/Stable
Classifier: Intended Audience :: Developers
Classifier: License :: OSI Approved :: MIT License
Classifier: Operating System :: OS Independent
Classifier: Programming Language :: Python :: 3
Classifier: Programming Language :: Python :: 3.7
Classifier: Programming Language :: Python :: 3.8
Classifier: Programming Language :: Python :: 3.9
Classifier: Programming Language :: Python :: 3.10
Classifier: Programming Language :: Python :: 3.11
Classifier: Topic :: Software Development :: Libraries :: Python Modules
Classifier: Topic :: Multimedia :: Graphics
Classifier: Topic :: Communications :: Chat
Requires-Python: >=3.7
Requires-Dist: Pillow>=9.0.0
Dynamic: author
Dynamic: author-email
Dynamic: classifier
Dynamic: description
Dynamic: description-content-type
Dynamic: home-page
Dynamic: keywords
Dynamic: project-url
Dynamic: requires-dist
Dynamic: requires-python
Dynamic: summary
